 [  
        {   
            "bh": "hgdgcc",  
            "gy": "陕西省西安市",  
            "name1": "张师傅"  ,
            "phone1": "15139878288" ,
            "name2": "邱亚楠",
            "phone2": "15139878288",
            "time1": "2017-04-10"
            
        }, 
        {  
            "bh": "vfvfvfv",  
            "gy": "陕西省宝鸡市",  
            "name1": "王海红"  ,
            "phone1": "15139878288" ,
            "name2": "李红",
            "phone2": "15139878288",
            "time1": "2017-04-10"
            
        },  
        {  
            "bh": "gtggg",  
            "gy": "陕西省渭南市",  
            "name1": "李淑芳"  ,
            "phone1": "15139878288" ,
            "name2": "马振",
            "phone2": "15139878288",
            "time1": "2017-04-10"
            
        },  
        {  
           "bh": "asdfghew",  
            "gy": "陕西省咸阳市",  
            "name1": "王世厅"  ,
            "phone1": "15139878288" ,
            "name2": "李辉",
            "phone2": "15139878288",
            "time1": "2017-04-10"
           
        },  
        {  
           "bh": "tyedfhjy",  
            "gy": "陕西省兴平市",  
            "name1": "白玉山"  ,
            "phone1": "15139878288" ,
            "name2": "甄伟涛",
            "phone2": "15139878288",
            "time1": "2017-04-10"
           
        },  
        {  
           "bh": "vbgedrth",  
            "gy": "陕西省延安市",  
            "name1": "李子柒"  ,
            "phone1": "15139878288" ,
            "name2": "朱金奇",
            "phone2": "15139878288",
            "time1": "2017-04-10"
            
        },  
        {  
           "bh": "bgrdvfes",  
            "gy": "陕西省榆林市",  
            "name1": "赵晓雷"  ,
            "phone1": "15139878288" ,
            "name2": "孙时长",
            "phone2": "15139878288",
            "time1": "2017-04-10"
           
        },  
        {  
           "bh": "cdffrthj",  
            "gy": "陕西省安康市",  
            "name1": "韩子怡"  ,
            "phone1": "15139878288" ,
            "name2": "旺盛达",
            "phone2": "15139878288",
            "time1": "2017-04-10"
           
        },  
        {  
           "bh": "wedfhuk",  
            "gy": "陕西省商洛市",  
            "name1": "李超"  ,
            "phone1": "15139878288" ,
            "name2": "来显示",
            "phone2": "15139878288",
            "time1": "2017-04-10"
            
        },  
        {  
           "bh": "qerfgyghj",  
            "gy": "陕西省商洛市",  
            "name1": "吕秀莲"  ,
            "phone1": "15139878288" ,
            "name2": "陈斯柯",
            "phone2": "15139878288",
            "time1": "2017-04-10"
             
        },  
        {  
           "bh": "pgtuihfd",  
            "gy": "陕西省商洛市",  
            "name1": "金子说"  ,
            "phone1": "15139878288" ,
            "name2": "珍秀妍",
            "phone2": "15139878288",
            "time1": "2017-04-10"
             
        },  
        {  
           "bh": "ljhtfrrr",  
            "gy": "陕西省商洛市",  
            "name1": "郝时间"  ,
            "phone1": "15139878288" ,
            "name2": "李海华",
            "phone2": "15139878288",
            "time1": "2017-04-10"
             
        },  
        {  
           "bh": "jfrtyuio",  
            "gy": "陕西省商洛市",  
            "name1": "张晓曦"  ,
            "phone1": "15139878288" ,
            "name2": "李多哈",
            "phone2": "15139878288",
            "time1": "2017-04-10"
             
        },  
        {  
           "bh": "rtytrwqa",  
            "gy": "陕西省商洛市",  
            "name1": "丁灿灿"  ,
            "phone1": "15139878288" ,
            "name2": "大好时",
            "phone2": "15139878288",
            "time1": "2017-04-10"
             
        },  
        {  
           "bh": "ytrewqwe",  
            "gy": "陕西省商洛市",  
            "name1": "丁立国"  ,
            "phone1": "15139878288" ,
            "name2": "赵晓丽",
            "phone2": "15139878288",
            "time1": "2017-04-10"
             
        },  
        {  
           "bh": "hteyuigff",  
            "gy": "陕西省商洛市",  
            "name1": "洛欧"  ,
            "phone1": "15139878288" ,
            "name2": "王志秀",
            "phone2": "15139878288",
            "time1": "2017-04-10"
             
        },  
        {  
           "bh": "JLDHererer",  
            "gy": "陕西省商洛市",  
            "name1": "孙贝尔"  ,
            "phone1": "15139878288" ,
            "name2": "金秀贤",
            "phone2": "15139878288",
            "time1": "2017-04-10"
             
        },  
        {  
           "bh": "eeerrrtr",  
            "gy": "陕西省商洛市",  
            "name1": "孙贝尔"  ,
            "phone1": "15139878288" ,
            "name2": "韩恩照",
            "phone2": "15139878288",
            "time1": "2017-04-10"
             
        },  
        {  
           "bh": "ddfrfrfrr",  
            "gy": "陕西省商洛市",  
            "name1": "孙贝尔"  ,
            "phone1": "15139878288" ,
            "name2": "张启迪",
            "phone2": "15139878288",
            "time1": "2017-04-10"
             
        },  
        {  
           "bh": "kikjuuh",  
            "gy": "陕西省商洛市",  
            "name1": "孙贝尔"  ,
            "phone1": "15139878288" ,
            "name2": "张启迪",
            "phone2": "15139878288",
            "time1": "2017-04-10"
             
        },  
        {  
           "bh": "eedede",  
            "gy": "陕西省商洛市",  
            "name1": "孙贝尔"  ,
            "phone1": "15139878288" ,
            "name2": "张启迪",
            "phone2": "15139878288",
            "time1": "2017-04-10"
             
        },  
        {  
           "bh": "frfrftgtt",  
            "gy": "陕西省商洛市",  
            "name1": "孙贝尔"  ,
            "phone1": "15139878288" ,
            "name2": "张启迪",
            "phone2": "15139878288",
            "time1": "2017-04-10"
             
        },  
        {  
           "bh": "tttttttg",  
            "gy": "陕西省商洛市",  
            "name1": "孙贝尔"  ,
            "phone1": "15139878288" ,
            "name2": "张启迪",
            "phone2": "15139878288",
            "time1": "2017-04-10"
             
        },  
        {  
           "bh": "yyuuythhyh",  
            "gy": "陕西省商洛市",  
            "name1": "孙贝尔"  ,
            "phone1": "15139878288" ,
            "name2": "张启迪",
            "phone2": "15139878288",
            "time1": "2017-04-10"
             
        },  
        {  
           "bh": "wwerrewww",  
            "gy": "陕西省商洛市",  
            "name1": "孙贝尔"  ,
            "phone1": "15139878288" ,
            "name2": "张启迪",
            "phone2": "15139878288",
            "time1": "2017-04-10"
             
        },  
        {  
           "bh": "tewwwert",  
            "gy": "陕西省商洛市",  
            "name1": "孙贝尔"  ,
            "phone1": "15139878288" ,
            "name2": "韩三岁",
            "phone2": "15139878288",
            "time1": "2017-04-10"
             
        },  
        {  
           "bh": "yuyuyu",  
            "gy": "陕西省商洛市",  
            "name1": "孙贝尔"  ,
            "phone1": "15139878288" ,
            "name2": "张启迪",
            "phone2": "15139878288",
            "time1": "2017-04-10"
             
        },  
        {  
           "bh": "werrreww",  
            "gy": "陕西省商洛市",  
            "name1": "孙贝尔"  ,
            "phone1": "15139878288" ,
            "name2": "张启迪",
            "phone2": "15139878288",
            "time1": "2017-04-10"
             
        },  
        {  
           "bh": "sawwsweftg",  
            "gy": "陕西省商洛市",  
            "name1": "孙贝尔"  ,
            "phone1": "15139878288" ,
            "name2": "张启迪",
            "phone2": "15139878288",
            "time1": "2017-04-10"
             
        },  
        {  
           "bh": "rfrwee33er",  
            "gy": "陕西省商洛市",  
            "name1": "孙贝尔"  ,
            "phone1": "15139878288" ,
            "name2": "张启迪",
            "phone2": "15139878288",
            "time1": "2017-04-10"
             
        },  
        {  
           "bh": "kikgffdf",  
            "gy": "陕西省商洛市",  
            "name1": "孙贝尔"  ,
            "phone1": "15139878288" ,
            "name2": "张启迪",
            "phone2": "15139878288",
            "time1": "2017-04-10"
             
        },  
        {  
           "bh": "rrwerccd",  
            "gy": "陕西省商洛市",  
            "name1": "孙贝尔"  ,
            "phone1": "15139878288" ,
            "name2": "张启迪",
            "phone2": "15139878288",
            "time1": "2017-04-10"
             
        },  
        {  
           "bh": "ghbfdgh",  
            "gy": "陕西省商洛市",  
            "name1": "孙贝尔"  ,
            "phone1": "15139878288" ,
            "name2": "张启迪",
            "phone2": "15139878288",
            "time1": "2017-04-10"
             
        },  
        {  
           "bh": "kgdrfgh",  
            "gy": "陕西省商洛市",  
            "name1": "孙贝尔"  ,
            "phone1": "15139878288" ,
            "name2": "张启迪",
            "phone2": "15139878288",
            "time1": "2017-04-10"
             
        },  
        {  
           "bh": "ugtygg",  
            "gy": "陕西省商洛市",  
            "name1": "孙贝尔"  ,
            "phone1": "15139878288" ,
            "name2": "张启迪",
            "phone2": "15139878288",
            "time1": "2017-04-10"
             
        },  
        {  
           "bh": "tyyuuu",  
            "gy": "陕西省商洛市",  
            "name1": "孙贝尔"  ,
            "phone1": "15139878288" ,
            "name2": "张启迪",
            "phone2": "15139878288",
            "time1": "2017-04-10"
             
        }
    ]  